abacus/__init__.py
abacus/core.py
abacus/entries_store.py
abacus/typer_cli/__init__.py
abacus/typer_cli/app.py
abacus/typer_cli/base.py
abacus/typer_cli/chart.py
abacus/typer_cli/ledger.py
abacus/typer_cli/post.py
abacus/typer_cli/show.py
abacus/user_chart.py
abacus/viewers.py
abacus_py-0.8.8.dist-info/LICENSE
abacus_py-0.8.8.dist-info/METADATA
abacus_py-0.8.8.dist-info/WHEEL
abacus_py-0.8.8.dist-info/entry_points.txt
abacus_py-0.8.8.dist-info/RECORD
