Metadata-Version: 2.1
Name: abacus-py
Version: 0.8.8
Summary: A minimal yet valid double-entry accounting system in Python.
Author: Evgeniy Pogrebnyak
Author-email: e.pogrebnyak@gmail.com
Requires-Python: >=3.8,<4.0
Classifier: Programming Language :: Python :: 3
Classifier: Programming Language :: Python :: 3.8
Classifier: Programming Language :: Python :: 3.9
Classifier: Programming Language :: Python :: 3.10
Classifier: Programming Language :: Python :: 3.11
Requires-Dist: pydantic (>=1.10.8,<2.0.0)
Requires-Dist: rich (>=13.3.5,<14.0.0)
Requires-Dist: typer (>=0.9.0,<0.10.0)
